mkdocs_cm_page_pdf/__init__.py
mkdocs_cm_page_pdf/plugin.py
mkdocs_page_pdf/__init__.py
mkdocs_page_pdf/plugin.py
mkdocs_cm_page_to_pdf-0.1.5.dist-info/LICENSE
mkdocs_cm_page_to_pdf-0.1.5.dist-info/METADATA
mkdocs_cm_page_to_pdf-0.1.5.dist-info/WHEEL
mkdocs_cm_page_to_pdf-0.1.5.dist-info/entry_points.txt
mkdocs_cm_page_to_pdf-0.1.5.dist-info/top_level.txt
mkdocs_cm_page_to_pdf-0.1.5.dist-info/RECORD
