Metadata-Version: 2.1
Name: mkdocs-cm-page-to-pdf
Version: 0.1.5
Summary: Generate a PDF file for each MkDocs page, with the possibility of selecting individual pages for export
Home-page: https://github.com/usulpt/mkdocs-cm-page-to-pdf
Author: usulpt
Author-email: 
License: MIT
Keywords: mkdocs pdf pyppeteer chrome headless page
Classifier: Development Status :: 4 - Beta
Classifier: Intended Audience :: Developers
Classifier: Intended Audience :: Information Technology
Classifier: License :: OSI Approved :: MIT License
Classifier: Programming Language :: Python
Classifier: Programming Language :: Python :: 3 :: Only
Classifier: Programming Language :: Python :: 3.6
Classifier: Programming Language :: Python :: 3.7
Classifier: Programming Language :: Python :: 3.8
Classifier: Programming Language :: Python :: 3.9
Requires-Python: >=3.6
License-File: LICENSE
Requires-Dist: mkdocs >=1.1
Requires-Dist: pyppeteer >=0.2
Requires-Dist: asyncio >=1.5
Requires-Dist: nest-asyncio >=1.5
